LICENSE
MANIFEST.in
README.md
setup.py
grove/__init__.py
grove/adc.py
grove/adc_8chan_12bit.py
grove/grove_12_chan_touch_sensor_MPR121.py
grove/grove_3_axis_compass_bmm150.py
grove/grove_4_digit_display.py
grove/grove_I2C_High_Accuracy_tem_hum_SHT35_sensor.py
grove/grove_air_quality_sensor_v1_3.py
grove/grove_button.py
grove/grove_collision_sensor.py
grove/grove_gesture_sensor.py
grove/grove_high_accuracy_temperature.py
grove/grove_i2c_color_sensor_v2.py
grove/grove_i2c_motor_driver.py
grove/grove_led.py
grove/grove_light_sensor_v1_2.py
grove/grove_loudness_sensor.py
grove/grove_mech_keycap.py
grove/grove_mini_pir_motion_sensor.py
grove/grove_moisture_sensor.py
grove/grove_oled_display_128x64.py
grove/grove_piezo_vibration_sensor.py
grove/grove_pwm_buzzer.py
grove/grove_recorder_v3_0.py
grove/grove_relay.py
grove/grove_rotary_angle_sensor.py
grove/grove_ryb_led_button.py
grove/grove_servo.py
grove/grove_slide_potentiometer.py
grove/grove_sound_sensor.py
grove/grove_switch.py
grove/grove_temperature_humidity_sensor.py
grove/grove_temperature_humidity_sensor_sht3x.py
grove/grove_temperature_sensor.py
grove/grove_thumb_joystick.py
grove/grove_tilt_switch.py
grove/grove_touch_sensor.py
grove/grove_touch_slider_CY8C.py
grove/grove_ultrasonic_ranger.py
grove/grove_uv_sensor.py
grove/grove_water_sensor.py
grove/i2c.py
grove.py.egg-info/PKG-INFO
grove.py.egg-info/SOURCES.txt
grove.py.egg-info/dependency_links.txt
grove.py.egg-info/entry_points.txt
grove.py.egg-info/not-zip-safe
grove.py.egg-info/requires.txt
grove.py.egg-info/top_level.txt
grove/button/__init__.py
grove/button/button.py
grove/button/button_gpio.py
grove/button/button_i2c.py
grove/factory/__init__.py
grove/factory/factory.py
grove/gpio/__init__.py
grove/gpio/gpio_mraa.py
grove/gpio/gpio_rpi.py
grove/gpio/wrapper.py
grove/helper/__init__.py
grove/helper/helper.py
grove/helper/os_sched.py
grove/lcd/__init__.py
grove/lcd/sh1107g.py
grove/led/__init__.py
grove/led/one_led.py
grove/led/one_led_ws2812.py
grove/motor/__init__.py
grove/motor/i2c_motor_driver.py
grove/temperature/__init__.py
grove/temperature/mcp9808.py
grove/temperature/temper.py